{"type":"PR","pr":{"number":24,"head":"57e183858a3f3a99ad6a7293d36e427888dca975"},"user":"nanito4.0vargas","status":"draft","branch":"cms/sistemas_aterramiento","collection":"servicios","title":"Sistemas de Aterramiento y Pararrayos","description":"Peritaje de sistemas eléctricos y puesta a tierra y mediciones en área comercial e industrial incluyendo pararrayos.","objects":{"entry":{"path":"src/pages/servicios/sistemas_aterramiento.md","sha":"512474828835a979356ec80077caf860c27862f9"},"files":[]},"timeStamp":"2019-09-05T15:28:44.177Z"}